sort_images/__init__.py
sort_images/__main__.py
sort_images/sort.py
sort_images/terminal_formatting.py
sort_images/version.py
sort_images-2025.10.21.dist-info/METADATA
sort_images-2025.10.21.dist-info/WHEEL
sort_images-2025.10.21.dist-info/entry_points.txt
sort_images-2025.10.21.dist-info/licenses/LICENSE.txt
sort_images-2025.10.21.dist-info/RECORD
