Metadata-Version: 2.4
Name: sort-images
Version: 2025.10.21
Summary: A cli tool to sort images into folders by date
Author-email: Guenthner <guenthner.jonathan@gmail.com>
License-File: LICENSE.txt
Keywords: Automation,Exif,Files,Images,Sorting
Classifier: License :: OSI Approved :: MIT License
Classifier: Operating System :: OS Independent
Classifier: Programming Language :: Python :: 3
Requires-Python: >=3.8
Requires-Dist: pillow
